EAACommander/__init__.py
EAACommander/cli_client.py
EAACommander/settings.ini
EAACommander/settings.py
tests/__init__.py
EAACommander-0.5.dist-info/LICENSE
EAACommander-0.5.dist-info/METADATA
EAACommander-0.5.dist-info/WHEEL
EAACommander-0.5.dist-info/entry_points.txt
EAACommander-0.5.dist-info/top_level.txt
EAACommander-0.5.dist-info/RECORD
