Metadata-Version: 2.1
Name: EAACommander
Version: 0.5
Summary: A tool for Electronically Assisted Astronomy (EAA) enthusiasts
Home-page: https://github.com/MarkoZnidar/EAACommander/
Author: Marko Žnidar
Author-email: marko.znidar@gmail.com
Classifier: Programming Language :: Python :: 3
Classifier: License :: OSI Approved :: MIT License
Classifier: Operating System :: OS Independent
Requires-Python: >=3.6
License-File: LICENSE
Requires-Dist: art
